bcut_asr_branch/__init__.py
bcut_asr_branch/__main__.py
bcut_asr_branch/orm.py
bcut_asr_branch-0.0.3.dist-info/entry_points.txt
bcut_asr_branch-0.0.3.dist-info/LICENSE
bcut_asr_branch-0.0.3.dist-info/METADATA
bcut_asr_branch-0.0.3.dist-info/WHEEL
bcut_asr_branch-0.0.3.dist-info/RECORD
