Metadata-Version: 2.1
Name: bcut-asr-branch
Version: 0.0.3
Summary: 使用必剪API的语音字幕识别
License: MIT
Author: SocialSisterYi
Author-email: 1440239038@qq.com
Requires-Python: >=3.10
Classifier: License :: OSI Approved :: MIT License
Classifier: Programming Language :: Python :: 3
Classifier: Programming Language :: Python :: 3.10
Classifier: Programming Language :: Python :: 3.11
Classifier: Programming Language :: Python :: 3.12
Requires-Dist: ffmpeg-python (>=0.2.0,<0.3.0)
Requires-Dist: pydantic (>=2.7.0,<3.0.0)
Requires-Dist: requests (>=2.31.0,<3.0.0)
